pandas_vet/__about__.py
pandas_vet/__init__.py
pandas_vet-2023.8.2.dist-info/METADATA
pandas_vet-2023.8.2.dist-info/WHEEL
pandas_vet-2023.8.2.dist-info/entry_points.txt
pandas_vet-2023.8.2.dist-info/licenses/LICENSE.txt
pandas_vet-2023.8.2.dist-info/RECORD
