Metadata-Version: 2.1
Name: pandas-vet
Version: 2023.8.2
Summary: A flake8 plugin to lint pandas in an opinionated way.
Project-URL: Homepage, https://github.com/deppen8/pandas-vet
Project-URL: Issues, https://github.com/deppen8/pandas-vet/issues
Author-email: Jacob Deppen <deppen.8@gmail.com>
License: MIT
License-File: LICENSE.txt
Keywords: flake8,linter,pandas,pandas-vet,qa
Classifier: Development Status :: 4 - Beta
Classifier: Environment :: Console
Classifier: Framework :: Flake8
Classifier: Intended Audience :: Developers
Classifier: License :: OSI Approved :: MIT License
Classifier: Programming Language :: Python
Classifier: Programming Language :: Python :: 3
Classifier: Programming Language :: Python :: 3 :: Only
Classifier: Programming Language :: Python :: 3.8
Classifier: Programming Language :: Python :: 3.9
Classifier: Programming Language :: Python :: 3.10
Classifier: Programming Language :: Python :: 3.11
Classifier: Topic :: Software Development :: Libraries :: Python Modules
Classifier: Topic :: Software Development :: Quality Assurance
Requires-Python: >=3.8
Requires-Dist: attrs>=19.2.0
Requires-Dist: flake8>=6.0.0
Provides-Extra: docs
Requires-Dist: jupyter-book; extra == 'docs'
Requires-Dist: sphinx; extra == 'docs'
